docs/conf.py
tabsim/__init__.py
tabsim/config.py
tabsim/plot.py
tabsim/read_ms.py
tabsim/sky.py
tabsim/tle.py
tabsim/tools.py
tabsim/write.py
tabsim/dask/__init__.py
tabsim/dask/coordinates.py
tabsim/dask/extras.py
tabsim/dask/interferometry.py
tabsim/dask/observation.py
tabsim/data/__init__.py
tabsim/data/config/sim_config_base.yaml
tabsim/data/config/tab_config_base.yaml
tabsim/data/rfi/norad_satellite.rfimodel
tabsim/data/rfi/satellite.ole
tabsim/data/rfi/satellite.rfimodel
tabsim/data/rfi/stationary.loc
tabsim/data/rfi/stationary.rfimodel
tabsim/data/rfi/tles/2023-02-21-navstar.json
tabsim/data/rfi/tles/2024-01-15-1T78VE.json
tabsim/data/rfi/tles/2024-01-15-ISS.json
tabsim/data/sky/calibrator.skymodel
tabsim/data/telescopes/EDA2.itrf.txt
tabsim/data/telescopes/MWA.itrf.txt
tabsim/data/telescopes/MeerKAT.itrf.txt
tabsim/data/telescopes/_telescopes.yaml
tabsim/jax/__init__.py
tabsim/jax/coordinates.py
tabsim/jax/interferometry.py
tabsim/jax/utils.py
tabsim/scripts/__init__.py
tabsim/scripts/ast_region.py
tabsim/scripts/flag_data.py
tabsim/scripts/import_tle_files.py
tabsim/scripts/setup_spacetrack_login.py
tabsim/scripts/sim_vis.py
tabsim/scripts/tle_sat_region.py
tabsim/scripts/write_config_from_ms.py
tabsim-0.0.13.dist-info/licenses/LICENSE
tests/test_basic.py
tests/test_sim-vis.py
tests/test_tle_api.py
tests/test_version.py
tabsim-0.0.13.dist-info/METADATA
tabsim-0.0.13.dist-info/WHEEL
tabsim-0.0.13.dist-info/entry_points.txt
tabsim-0.0.13.dist-info/top_level.txt
tabsim-0.0.13.dist-info/RECORD
