Metadata-Version: 2.4
Name: tabsim
Version: 0.0.13
Summary: Trajectory-based Radio Frequency Interference (RFI) simulations for radio interferometeric data.
Author-email: Chris Finlay <christopher.finlay@epfl.ch>
Maintainer-email: Chris Finlay <christopher.finlay@epfl.ch>
License:                     GNU GENERAL PUBLIC LICENSE
Project-URL: Repository, https://github.com/chrisfinlay/tab-sim.git
Requires-Python: >=3.9
License-File: LICENSE
Requires-Dist: jax
Requires-Dist: dask
Requires-Dist: xarray
Requires-Dist: zarr<3.0.0
Requires-Dist: dask-ms>=0.2.21
Requires-Dist: scipy
Requires-Dist: tqdm
Requires-Dist: matplotlib
Requires-Dist: astropy
Requires-Dist: spacetrack
Requires-Dist: skyfield
Requires-Dist: numpy
Requires-Dist: pyyaml
Provides-Extra: gpu
Requires-Dist: jax[cuda12]; extra == "gpu"
Provides-Extra: sat
Requires-Dist: regions; extra == "sat"
Provides-Extra: ipy
Requires-Dist: ipython; extra == "ipy"
Requires-Dist: ipykernel; extra == "ipy"
Provides-Extra: test
Requires-Dist: pytest; extra == "test"
Provides-Extra: docs
Requires-Dist: sphinx; extra == "docs"
Requires-Dist: sphinx-rtd-theme; extra == "docs"
Dynamic: license-file
